ynam/__init__.py
ynam/__main__.py
ynam/_version.py
ynam/main.py
ynam/mint_api.py
ynam/quickstart.py
ynam/ynab_api.py
ynam/ynam_parser.py
ynam/ynam_secrets.py
ynam-0.4.0.post2.dist-info/LICENSE
ynam-0.4.0.post2.dist-info/METADATA
ynam-0.4.0.post2.dist-info/WHEEL
ynam-0.4.0.post2.dist-info/entry_points.txt
ynam-0.4.0.post2.dist-info/top_level.txt
ynam-0.4.0.post2.dist-info/RECORD
