Metadata-Version: 2.1
Name: ynam
Version: 0.4.0.post2
Summary: Automate importing of Mint transactions into YNAB
Home-page: https://github.com/snowskeleton/ynam
Author: snowskeleton
Author-email: isaac@snowskeleton.net
License: Apache 2.0
License-File: LICENSE
Requires-Dist: mintapi
